easyscrapper/__init__.py
easyscrapper/cli.py
easyscrapper/scraper.py
easyscrapper/utils.py
easyscrapper-1.0.2.dist-info/licenses/LICENSE
easyscrapper-1.0.2.dist-info/METADATA
easyscrapper-1.0.2.dist-info/WHEEL
easyscrapper-1.0.2.dist-info/entry_points.txt
easyscrapper-1.0.2.dist-info/top_level.txt
easyscrapper-1.0.2.dist-info/RECORD
