Metadata-Version: 2.4
Name: easyscrapper
Version: 1.0.2
Summary: easyscrapper is a fast, lightweight Python package and CLI tool that lets developers, data scientists, and AI engineers extract text, HTML, emails, links, canonical, meta and images from any public webpage - perfect for AI, RAG pipelines, SEO, content aggregation, and scalable data workflows with just one command or a few lines of code.
Home-page: https://github.com/krishnatadi/easyscrapper
Author: Krishna Tadi
Author-email: er.krishnatadi@gmail.com
License: MIT
Project-URL: Documentation, https://github.com/krishnatadi/easyscrapper#readme
Project-URL: Source, https://github.com/krishnatadi/easyscrapper
Project-URL: Issue Tracker, https://github.com/krishnatadi/easyscrapper/issues
Keywords: web scraping,data extraction,html parser,scraping,easyscrapper,RAG,AI,Text Chuncking
Classifier: Programming Language :: Python
Classifier: License :: OSI Approved :: MIT License
Classifier: Operating System :: OS Independent
Classifier: Intended Audience :: Developers
Classifier: Development Status :: 5 - Production/Stable
Classifier: Environment :: Console
Requires-Python: >=3.6
License-File: LICENSE
Requires-Dist: requests
Requires-Dist: beautifulsoup4
Dynamic: author
Dynamic: author-email
Dynamic: classifier
Dynamic: description
Dynamic: description-content-type
Dynamic: home-page
Dynamic: keywords
Dynamic: license
Dynamic: license-file
Dynamic: project-url
Dynamic: requires-dist
Dynamic: requires-python
Dynamic: summary
